{
    "time": {
        "cpu_time_user": "00:02:13.650",
        "cpu_time_system": "00:00:08.689",
        "runtime": "00:00:24.048",
        "cpu_time_iowait": "00:00:00.000"
    },
    "peak_resources": {
        "cpu_percent": 1554.7,
        "memory_rss": "907MiB",
        "memory_vms": "1GiB",
        "threads": 33
    },
    "avg_resources": {
        "cpu_percent": 585.991701244813,
        "memory_rss": "654MiB",
        "memory_vms": "1GiB",
        "threads": 32.207468879668056
    }
}