{
    "time": {
        "cpu_time_user": "00:00:04.099",
        "cpu_time_system": "00:00:00.110",
        "runtime": "00:00:04.224",
        "cpu_time_iowait": "00:00:00.000"
    },
    "peak_resources": {
        "cpu_percent": 109.7,
        "memory_rss": "232MiB",
        "memory_vms": "386MiB",
        "threads": 2
    },
    "avg_resources": {
        "cpu_percent": 95.14772727272724,
        "memory_rss": "165MiB",
        "memory_vms": "308MiB",
        "threads": 1.9090909090909092
    }
}