{
    "time": {
        "cpu_time_user": "00:00:10.730",
        "cpu_time_system": "00:00:00.900",
        "runtime": "00:00:11.691",
        "cpu_time_iowait": "00:00:00.000"
    },
    "peak_resources": {
        "cpu_percent": 109.6,
        "memory_rss": "353MiB",
        "memory_vms": "367MiB",
        "threads": 2
    },
    "avg_resources": {
        "cpu_percent": 97.78050847457628,
        "memory_rss": "184MiB",
        "memory_vms": "196MiB",
        "threads": 1.576271186440678
    }
}